{
  "best_metric": null,
  "best_model_checkpoint": null,
  "epoch": 1.0,
  "eval_steps": 500,
  "global_step": 287,
  "is_hyper_param_search": false,
  "is_local_process_zero": true,
  "is_world_process_zero": true,
  "log_history": [
    {
      "epoch": 0.34904013961605584,
      "grad_norm": NaN,
      "learning_rate": 1.9983775409361447e-05,
      "loss": 78.4474,
      "step": 100
    },
    {
      "epoch": 0.6980802792321117,
      "grad_norm": NaN,
      "learning_rate": 1.8943080519551108e-05,
      "loss": 0.0,
      "step": 200
    },
    {
      "epoch": 1.0,
      "eval_loss": NaN,
      "eval_runtime": 151.9181,
      "eval_samples_per_second": 6.701,
      "eval_steps_per_second": 0.421,
      "step": 287
    }
  ],
  "logging_steps": 100,
  "max_steps": 858,
  "num_input_tokens_seen": 0,
  "num_train_epochs": 3,
  "save_steps": 500,
  "stateful_callbacks": {
    "TrainerControl": {
      "args": {
        "should_epoch_stop": false,
        "should_evaluate": false,
        "should_log": false,
        "should_save": true,
        "should_training_stop": false
      },
      "attributes": {}
    }
  },
  "total_flos": 5.286635086702182e+16,
  "train_batch_size": 4,
  "trial_name": null,
  "trial_params": null
}
